bootstrap.py
buildout.cfg
setup.py
src/zeomega/__init__.py
src/zeomega.recipe.mxodbcconnect.egg-info/PKG-INFO
src/zeomega.recipe.mxodbcconnect.egg-info/SOURCES.txt
src/zeomega.recipe.mxodbcconnect.egg-info/dependency_links.txt
src/zeomega.recipe.mxodbcconnect.egg-info/entry_points.txt
src/zeomega.recipe.mxodbcconnect.egg-info/namespace_packages.txt
src/zeomega.recipe.mxodbcconnect.egg-info/requires.txt
src/zeomega.recipe.mxodbcconnect.egg-info/top_level.txt
src/zeomega.recipe.mxodbcconnect.egg-info/zip-safe
src/zeomega/recipe/__init__.py
src/zeomega/recipe/mxodbcconnect/__init__.py