Metadata-Version: 1.0
Name: zeomega.recipe.mxodbcconnect
Version: 0.3
Summary: A buildout recipe to install eGenix mx.ODBCConnect.Client
Home-page: http://www.zeomega.com
Author: Senthil
Author-email: orsenthil@gmail.com
License: GPL
Keywords: Buildout recipe mx.ODBCConnect.Client
Platform: UNKNOWN
Classifier: Development Status :: 3 - Alpha
Classifier: Environment :: Plugins
Classifier: Intended Audience :: System Administrators
Classifier: Framework :: Buildout
Classifier: License :: OSI Approved :: GNU General Public License (GPL)
Classifier: Natural Language :: English
Classifier: Operating System :: POSIX :: Linux
Classifier: Programming Language :: Python
Classifier: Topic :: Database
Classifier: Topic :: System :: Installation/Setup
Classifier: Topic :: Software Development :: Libraries :: Python Modules
